{
  "job_list": [
    {
      "jobTitle": "Full-stack Javascript developer",
      "primaryRole": "",
      "typeOfPosition": "Full-time",
      "location": "Remote",
      "companyName": "NFT Port",
      "isFeatured": false,
      "isRemote": false,

      "postTime": "2022-09-29T19:15",
      "logo": "avatar.jpg",
      "keywords": ["C++", "backend", "web3"],
      "compensation": {
        "minimum": "100k USD",
        "maximum": "110k USD"
      },
      "applyLink": "",
      "jobDescription": ""
    }
  ]
}
